{"train_no": "410", "has_breastfeeding_rooms": false, "carries_packages": false, "has_dining_rooms": false, "is_accessible": true, "has_bike_stands": false, "train_class": "1109", "stops": [{"station": "1012", "departs_at": "07:37", "arrives_at": "07:35"}, {"station": "1011", "departs_at": "07:46", "arrives_at": "07:44"}, {"station": "1008", "departs_at": "07:59", "arrives_at": "07:55"}, {"station": "1007", "departs_at": "08:07", "arrives_at": "08:06"}, {"station": "1715", "departs_at": "10:22", "arrives_at": "10:19"}, {"station": "1616", "departs_at": "11:03", "arrives_at": "11:01"}, {"station": "1619", "departs_at": "11:19", "arrives_at": "11:18"}, {"station": "1624", "departs_at": "11:38", "arrives_at": "11:37"}, {"station": "1626", "departs_at": "11:56", "arrives_at": "11:54"}, {"station": "1632", "departs_at": "12:22", "arrives_at": "12:20"}]}